aelog/__init__.py
aelog/aelog.py
aelog/consts.py
aelog/log.py
aelog-1.0.9.dist-info/LICENSE
aelog-1.0.9.dist-info/METADATA
aelog-1.0.9.dist-info/WHEEL
aelog-1.0.9.dist-info/top_level.txt
aelog-1.0.9.dist-info/RECORD
