Metadata-Version: 2.1
Name: aelog
Version: 1.0.9
Summary: An simple, async, full package name path, log rotating, different colored log library.
Home-page: https://github.com/tinybees/aelog
Author: TinyBees
Author-email: a598824322@qq.com
License: MIT
Keywords: log,logging,colored,async,asynchronous,simple,rotating
Platform: UNKNOWN
Classifier: Development Status :: 5 - Production/Stable
Classifier: Intended Audience :: Developers
Classifier: License :: OSI Approved :: MIT License
Classifier: Natural Language :: Chinese (Simplified)
Classifier: Operating System :: POSIX
Classifier: Operating System :: Microsoft :: Windows
Classifier: Operating System :: MacOS :: MacOS X
Classifier: Topic :: Software Development :: Libraries :: Python Modules
Classifier: Topic :: Utilities
Classifier: Programming Language :: Python
Classifier: Programming Language :: Python :: 3.6
Classifier: Programming Language :: Python :: 3.7
Classifier: Programming Language :: Python :: 3.8
Requires: colorlog
Requires-Python: >=3.6
Requires-Dist: colorlog (>=3.1.0)
